torch_constrained/__init__.py
torch_constrained/constrained_optimizer.py
torch_constrained/extragradient.py
torch_constrained-0.0.27.dist-info/LICENSE.md
torch_constrained-0.0.27.dist-info/METADATA
torch_constrained-0.0.27.dist-info/WHEEL
torch_constrained-0.0.27.dist-info/top_level.txt
torch_constrained-0.0.27.dist-info/RECORD
