Metadata-Version: 2.1
Name: torch-constrained
Version: 0.0.27
Summary: Torch Optimizer for constrained optimization problems
Home-page: https://github.com/manuel-delverme/constrained_optimization
Author: Manuel Del Verme
Author-email: manuel.delverme@gmail.com
License: UNKNOWN
Project-URL: Bug Tracker, https://github.com/manuel-delverme/constrained_optimization/issues
Platform: UNKNOWN
Classifier: Programming Language :: Python :: 3
Classifier: Operating System :: OS Independent
Requires-Python: >=3.6
License-File: LICENSE.md
